terminal_controller_uvx/__init__.py
terminal_controller_uvx/core.py
terminal_controller_uvx-0.1.4.dist-info/LICENSE
terminal_controller_uvx-0.1.4.dist-info/METADATA
terminal_controller_uvx-0.1.4.dist-info/WHEEL
terminal_controller_uvx-0.1.4.dist-info/entry_points.txt
terminal_controller_uvx-0.1.4.dist-info/top_level.txt
terminal_controller_uvx-0.1.4.dist-info/RECORD
