Metadata-Version: 2.2
Name: terminal-controller-uvx
Version: 0.1.4
Summary: A terminal controller MCP server for UVx
Home-page: https://github.com/GongRzhe/terminal-controller-uvx
Author: UVx Project
Author-email: UVx Project <info@uvx.org>
License: MIT
Project-URL: Homepage, https://github.com/GongRzhe/terminal-controller-uvx
Project-URL: Issues, https://github.com/GongRzhe/terminal-controller-uvx/issues
Classifier: Programming Language :: Python :: 3
Classifier: License :: OSI Approved :: MIT License
Classifier: Operating System :: OS Independent
Requires-Python: >=3.10
License-File: LICENSE
Requires-Dist: mcp>=0.1.0
Dynamic: author
Dynamic: home-page
Dynamic: requires-python
